README.txt
setup.py
docs/HISTORY.txt
rt/__init__.py
rt.searchtitlegroups.egg-info/PKG-INFO
rt.searchtitlegroups.egg-info/SOURCES.txt
rt.searchtitlegroups.egg-info/dependency_links.txt
rt.searchtitlegroups.egg-info/entry_points.txt
rt.searchtitlegroups.egg-info/namespace_packages.txt
rt.searchtitlegroups.egg-info/not-zip-safe
rt.searchtitlegroups.egg-info/requires.txt
rt.searchtitlegroups.egg-info/top_level.txt
rt/searchtitlegroups/__init__.py
rt/searchtitlegroups/config.py
rt/searchtitlegroups/configure.zcml
rt/searchtitlegroups/patches.py
rt/searchtitlegroups/Extensions/update_zope_groups.py
rt/searchtitlegroups/browser/__init__.py
rt/searchtitlegroups/browser/configure.zcml
rt/searchtitlegroups/browser/searchGroups.py
rt/searchtitlegroups/profiles/default/metadata.xml
rt/searchtitlegroups/profiles/default/skins.xml
rt/searchtitlegroups/skins/search_title_groups/prefs_group_edit.py
rt/searchtitlegroups/skins/search_title_groups/prefs_groups_overview.cpt
rt/searchtitlegroups/skins/search_title_groups/prefs_groups_overview.cpt.metadata