Metadata-Version: 1.0
Name: rt.searchtitlegroups
Version: 1.2
Summary: Fixed the update of the Zope's groups and search in title of the groups
Home-page: UNKNOWN
Author: RedTurtle Technology
Author-email: sviluppoplone@redturtle.it
License: GPL
Platform: UNKNOWN
Classifier: Programming Language :: Python
Classifier: Topic :: Software Development :: Libraries :: Python Modules
